AminoLightPy/__init__.py
AminoLightPy/abstract_client.py
AminoLightPy/acm.py
AminoLightPy/amino_socket.py
AminoLightPy/client.py
AminoLightPy/constants.py
AminoLightPy/managers.py
AminoLightPy/sub_client.py
AminoLightPy/lib/__init__.py
AminoLightPy/lib/util/__init__.py
AminoLightPy/lib/util/exceptions.py
AminoLightPy/lib/util/helpers.py
AminoLightPy/lib/util/objects.py
AminoLightPy/lib/util/utils.py
amino_light_py-0.2.3.dist-info/licenses/LICENSE
amino_light_py-0.2.3.dist-info/METADATA
amino_light_py-0.2.3.dist-info/WHEEL
amino_light_py-0.2.3.dist-info/top_level.txt
amino_light_py-0.2.3.dist-info/RECORD
