Metadata-Version: 2.4
Name: amino.light.py
Version: 0.2.3
Summary: Best Amino.py alternative
Home-page: https://github.com/AugustLigh/AminoLightPy
Author: AugustLight
License: MIT
Keywords: amino,aminoapps,amino.fix,amino.light,amino.ligt.py,AminoLightPy,amino-bot,narvii,medialab,api,python,python3,python3.x,minori,august,augustlight,aminolightpy,amino.py
Classifier: Intended Audience :: Developers
Classifier: License :: OSI Approved :: MIT License
Classifier: Programming Language :: Python :: 3.9
Classifier: Programming Language :: Python :: 3.10
Classifier: Programming Language :: Python :: 3.11
Classifier: Programming Language :: Python :: 3.12
Classifier: Programming Language :: Python :: 3.13
License-File: LICENSE
Requires-Dist: requests
Requires-Dist: websocket-client
Dynamic: author
Dynamic: classifier
Dynamic: description
Dynamic: description-content-type
Dynamic: home-page
Dynamic: keywords
Dynamic: license
Dynamic: license-file
Dynamic: requires-dist
Dynamic: summary
